sequential/__init__.py
sequential/_version.py
sequential/csp_global.py
sequential/csp_local.py
sequential/dpm.py
sequential/pat2feat.py
sequential/seq2pat.py
sequential/utils.py
sequential/backend/build_mdd.cpp
sequential/backend/build_mdd.hpp
sequential/backend/freq_miner.cpp
sequential/backend/freq_miner.hpp
sequential/backend/node_mdd.cpp
sequential/backend/node_mdd.hpp
sequential/backend/pattern.hpp
sequential/backend/seq2pat.cpp
sequential/backend/seq2pat.hpp
sequential/backend/seq2pat.pxd
sequential/backend/seq_to_pat.cpp
sequential/backend/seq_to_pat.cpython-38-darwin.so
sequential/backend/seq_to_pat.html
sequential/backend/seq_to_pat.pyx
seq2pat-2.0.0.dist-info/LICENSE
seq2pat-2.0.0.dist-info/METADATA
seq2pat-2.0.0.dist-info/NOTICES.txt
seq2pat-2.0.0.dist-info/WHEEL
seq2pat-2.0.0.dist-info/top_level.txt
seq2pat-2.0.0.dist-info/RECORD
