Metadata-Version: 2.1
Name: seq2pat
Version: 2.0.0
Summary: Seq2Pat: Sequence-to-Pattern Generation Library
Home-page: https://github.com/fidelity/seq2pat
Author: FMR LLC
Project-URL: Documentation, https://fidelity.github.io/seq2pat/
Project-URL: Source, https://github.com/fidelity/seq2pat
Classifier: License :: OSI Approved :: GNU General Public License v2 (GPLv2)
Classifier: Programming Language :: Python :: 3.8
Classifier: Operating System :: OS Independent
License-File: LICENSE
License-File: NOTICES.txt
Requires-Dist: cython >=0.29.13
Requires-Dist: ortools
Requires-Dist: numpy
Requires-Dist: pandas
Requires-Dist: joblib
